setup.py
nonNewtonianIcoFlux/__init__.py
nonNewtonianIcoFlux.egg-info/PKG-INFO
nonNewtonianIcoFlux.egg-info/SOURCES.txt
nonNewtonianIcoFlux.egg-info/dependency_links.txt
nonNewtonianIcoFlux.egg-info/entry_points.txt
nonNewtonianIcoFlux.egg-info/requires.txt
nonNewtonianIcoFlux.egg-info/top_level.txt
nonNewtonianIcoFlux.egg-info/zip-safe
nonNewtonianIcoFlux/r1_6/__init__.py
nonNewtonianIcoFlux/r1_6_dev/__init__.py
nonNewtonianIcoFlux/r2_0_0/__init__.py
nonNewtonianIcoFlux/r2_1_1/__init__.py