Metadata-Version: 1.0
Name: nonNewtonianIcoFlux
Version: 2.1
Summary: Python front-end of the nonNewtonianIcoFoam
Home-page: http://sourceforge.net/projects/pythonFlu
Author: Alexey Petrov
Author-email: alexey.petrov.nnov@gmail.com
License: GPL
Platform: linux
Classifier: Development Status :: 3 - Alpha
Classifier: Environment :: Console
Classifier: Intended Audience :: Science/Research
Classifier: License :: OSI Approved :: GNU General Public License (GPL)
Classifier: Operating System :: POSIX
Classifier: Programming Language :: Python
Classifier: Topic :: Scientific/Engineering
